LICENSE
README.md
setup.py
.github/workflows/test.yaml
pycolumns/__init__.py
pycolumns/column.py
pycolumns/columns.py
pycolumns/indices.py
pycolumns/mergesort.py
pycolumns/sfile.py
pycolumns/util.py
pycolumns/version.py
pycolumns.egg-info/PKG-INFO
pycolumns.egg-info/SOURCES.txt
pycolumns.egg-info/dependency_links.txt
pycolumns.egg-info/requires.txt
pycolumns.egg-info/top_level.txt
pycolumns/tests/__init__.py
pycolumns/tests/test_create.py
pycolumns/tests/test_create_index.py
pycolumns/tests/test_query.py