Metadata-Version: 2.1
Name: pycolumns
Version: 1.0.0
Summary: A simple, efficient, pythonic column data store
Home-page: https://github.com/esheldon/pycolumns
License: MIT
License-File: LICENSE
